django_dotnetid/__init__.py
django_dotnetid/adapter.py
django_dotnetid/apps.py
django_dotnetid/provider.py
django_dotnetid/urls.py
django_dotnetid/views.py
django_dotnetid-1.0.0.dist-info/licenses/LICENSE
django_dotnetid-1.0.0.dist-info/METADATA
django_dotnetid-1.0.0.dist-info/WHEEL
django_dotnetid-1.0.0.dist-info/top_level.txt
django_dotnetid-1.0.0.dist-info/RECORD
