Metadata-Version: 2.4
Name: django-dotnetid
Version: 1.0.0
Summary: A django-allauth dotnetid provider
Author-email: SITN <sitn@ne.ch>, maltaesousa <stephane.maltaesousa@ne.ch>
Project-URL: Homepage, https://github.com/sitn/sitn-django-plugins
Project-URL: Issues, https://github.com/sitn/sitn-django-plugins/issues
Classifier: Environment :: Web Environment
Classifier: Framework :: Django
Classifier: Framework :: Django :: 5.0
Classifier: Intended Audience :: Developers
Classifier: Operating System :: OS Independent
Classifier: Programming Language :: Python
Classifier: Programming Language :: Python :: 3
Classifier: Programming Language :: Python :: 3 :: Only
Classifier: Programming Language :: Python :: 3.10
Classifier: Programming Language :: Python :: 3.11
Classifier: Programming Language :: Python :: 3.12
Classifier: Topic :: Internet :: WWW/HTTP
Classifier: Topic :: Internet :: WWW/HTTP :: Dynamic Content
Requires-Python: >=3.13
License-File: LICENSE
Requires-Dist: Django>=5.0
Dynamic: license-file
